{"errors":[],"warnings":[],"namedChunkGroups":{"app":{"chunks":[9,1,0,2],"assets":["webpack-runtime-340fb8892d2e56f72438.js","webpack-runtime-340fb8892d2e56f72438.js.map","styles.2c4d21b2a6b5cd409e8b.css","styles-4a10d40ae0bc7b56294a.js","styles-4a10d40ae0bc7b56294a.js.map","commons-68e97ec511a6ffc68199.js","commons-68e97ec511a6ffc68199.js.map","app-699990a931ae60dec19a.js","app-699990a931ae60dec19a.js.map"],"children":{},"childAssets":{}},"component---src-templates-blog-js":{"chunks":[1,0,8],"assets":["styles.2c4d21b2a6b5cd409e8b.css","styles-4a10d40ae0bc7b56294a.js","styles-4a10d40ae0bc7b56294a.js.map","commons-68e97ec511a6ffc68199.js","commons-68e97ec511a6ffc68199.js.map","component---src-templates-blog-js-0d18f705ba614ca102be.js","component---src-templates-blog-js-0d18f705ba614ca102be.js.map"],"children":{},"childAssets":{}},"component---src-pages-404-js":{"chunks":[1,0,3],"assets":["styles.2c4d21b2a6b5cd409e8b.css","styles-4a10d40ae0bc7b56294a.js","styles-4a10d40ae0bc7b56294a.js.map","commons-68e97ec511a6ffc68199.js","commons-68e97ec511a6ffc68199.js.map","component---src-pages-404-js-4fd339943c719c0110d4.js","component---src-pages-404-js-4fd339943c719c0110d4.js.map"],"children":{},"childAssets":{}},"component---src-pages-about-js":{"chunks":[1,0,4],"assets":["styles.2c4d21b2a6b5cd409e8b.css","styles-4a10d40ae0bc7b56294a.js","styles-4a10d40ae0bc7b56294a.js.map","commons-68e97ec511a6ffc68199.js","commons-68e97ec511a6ffc68199.js.map","component---src-pages-about-js-2755899f2a29f4829397.js","component---src-pages-about-js-2755899f2a29f4829397.js.map"],"children":{},"childAssets":{}},"component---src-pages-blog-js":{"chunks":[1,0,5],"assets":["styles.2c4d21b2a6b5cd409e8b.css","styles-4a10d40ae0bc7b56294a.js","styles-4a10d40ae0bc7b56294a.js.map","commons-68e97ec511a6ffc68199.js","commons-68e97ec511a6ffc68199.js.map","component---src-pages-blog-js-dd4b945c7da19c356116.js","component---src-pages-blog-js-dd4b945c7da19c356116.js.map"],"children":{},"childAssets":{}},"component---src-pages-contact-js":{"chunks":[1,0,6],"assets":["styles.2c4d21b2a6b5cd409e8b.css","styles-4a10d40ae0bc7b56294a.js","styles-4a10d40ae0bc7b56294a.js.map","commons-68e97ec511a6ffc68199.js","commons-68e97ec511a6ffc68199.js.map","component---src-pages-contact-js-790059ffc190ae24be10.js","component---src-pages-contact-js-790059ffc190ae24be10.js.map"],"children":{},"childAssets":{}},"component---src-pages-index-js":{"chunks":[1,0,7],"assets":["styles.2c4d21b2a6b5cd409e8b.css","styles-4a10d40ae0bc7b56294a.js","styles-4a10d40ae0bc7b56294a.js.map","commons-68e97ec511a6ffc68199.js","commons-68e97ec511a6ffc68199.js.map","component---src-pages-index-js-048eda98805b7d6527e7.js","component---src-pages-index-js-048eda98805b7d6527e7.js.map"],"children":{},"childAssets":{}}},"assetsByChunkName":{"app":["webpack-runtime-340fb8892d2e56f72438.js","styles.2c4d21b2a6b5cd409e8b.css","styles-4a10d40ae0bc7b56294a.js","commons-68e97ec511a6ffc68199.js","app-699990a931ae60dec19a.js"],"component---src-templates-blog-js":["styles.2c4d21b2a6b5cd409e8b.css","styles-4a10d40ae0bc7b56294a.js","commons-68e97ec511a6ffc68199.js","component---src-templates-blog-js-0d18f705ba614ca102be.js"],"component---src-pages-404-js":["styles.2c4d21b2a6b5cd409e8b.css","styles-4a10d40ae0bc7b56294a.js","commons-68e97ec511a6ffc68199.js","component---src-pages-404-js-4fd339943c719c0110d4.js"],"component---src-pages-about-js":["styles.2c4d21b2a6b5cd409e8b.css","styles-4a10d40ae0bc7b56294a.js","commons-68e97ec511a6ffc68199.js","component---src-pages-about-js-2755899f2a29f4829397.js"],"component---src-pages-blog-js":["styles.2c4d21b2a6b5cd409e8b.css","styles-4a10d40ae0bc7b56294a.js","commons-68e97ec511a6ffc68199.js","component---src-pages-blog-js-dd4b945c7da19c356116.js"],"component---src-pages-contact-js":["styles.2c4d21b2a6b5cd409e8b.css","styles-4a10d40ae0bc7b56294a.js","commons-68e97ec511a6ffc68199.js","component---src-pages-contact-js-790059ffc190ae24be10.js"],"component---src-pages-index-js":["styles.2c4d21b2a6b5cd409e8b.css","styles-4a10d40ae0bc7b56294a.js","commons-68e97ec511a6ffc68199.js","component---src-pages-index-js-048eda98805b7d6527e7.js"]}}